{
	"archive" : {},
	"artifacts" : 
	[
		{
			"path" : "libs/libmuninn.a"
		}
	],
	"backtrace" : 1,
	"backtraceGraph" : 
	{
		"commands" : 
		[
			"add_library",
			"include_directories"
		],
		"files" : 
		[
			"modules/muninn/external/muninn/muninn/CMakeLists.txt",
			"modules/muninn/external/CMakeLists.txt"
		],
		"nodes" : 
		[
			{
				"file" : 0
			},
			{
				"command" : 0,
				"file" : 0,
				"line" : 1,
				"parent" : 0
			},
			{
				"file" : 1
			},
			{
				"command" : 1,
				"file" : 1,
				"line" : 8,
				"parent" : 2
			}
		]
	},
	"compileGroups" : 
	[
		{
			"compileCommandFragments" : 
			[
				{
					"fragment" : " -Wall -O0 -ggdb  "
				}
			],
			"includes" : 
			[
				{
					"backtrace" : 3,
					"path" : "/mnt/c/Users/juhasm/Documents/phaistos/modules/muninn/external/muninn"
				},
				{
					"backtrace" : 3,
					"path" : "/mnt/c/Users/juhasm/Documents/phaistos/modules/muninn/external/muninn/external"
				}
			],
			"language" : "CXX",
			"sourceIndexes" : 
			[
				0,
				1,
				2,
				3,
				4,
				5,
				6,
				7,
				8,
				9,
				10,
				11,
				12,
				13
			]
		}
	],
	"id" : "muninn::@9178704d702a84e07399",
	"name" : "muninn",
	"nameOnDisk" : "libmuninn.a",
	"paths" : 
	{
		"build" : "modules/.phase1/muninn/external/muninn/muninn",
		"source" : "modules/muninn/external/muninn/muninn"
	},
	"sourceGroups" : 
	[
		{
			"name" : "Source Files",
			"sourceIndexes" : 
			[
				0,
				1,
				2,
				3,
				4,
				5,
				6,
				7,
				8,
				9,
				10,
				11,
				12,
				13
			]
		}
	],
	"sources" : 
	[
		{
			"backtrace" : 1,
			"compileGroupIndex" : 0,
			"path" : "modules/muninn/external/muninn/muninn/CGE.cpp",
			"sourceGroupIndex" : 0
		},
		{
			"backtrace" : 1,
			"compileGroupIndex" : 0,
			"path" : "modules/muninn/external/muninn/muninn/GE.cpp",
			"sourceGroupIndex" : 0
		},
		{
			"backtrace" : 1,
			"compileGroupIndex" : 0,
			"path" : "modules/muninn/external/muninn/muninn/Factories/CGEfactory.cpp",
			"sourceGroupIndex" : 0
		},
		{
			"backtrace" : 1,
			"compileGroupIndex" : 0,
			"path" : "modules/muninn/external/muninn/muninn/Histories/MultiHistogramHistory.cpp",
			"sourceGroupIndex" : 0
		},
		{
			"backtrace" : 1,
			"compileGroupIndex" : 0,
			"path" : "modules/muninn/external/muninn/muninn/MLE/MLE.cpp",
			"sourceGroupIndex" : 0
		},
		{
			"backtrace" : 1,
			"compileGroupIndex" : 0,
			"path" : "modules/muninn/external/muninn/muninn/tools/CanonicalAverager.cpp",
			"sourceGroupIndex" : 0
		},
		{
			"backtrace" : 1,
			"compileGroupIndex" : 0,
			"path" : "modules/muninn/external/muninn/muninn/utils/utils.cpp",
			"sourceGroupIndex" : 0
		},
		{
			"backtrace" : 1,
			"compileGroupIndex" : 0,
			"path" : "modules/muninn/external/muninn/muninn/utils/TArrayUtils.cpp",
			"sourceGroupIndex" : 0
		},
		{
			"backtrace" : 1,
			"compileGroupIndex" : 0,
			"path" : "modules/muninn/external/muninn/muninn/utils/timer.cpp",
			"sourceGroupIndex" : 0
		},
		{
			"backtrace" : 1,
			"compileGroupIndex" : 0,
			"path" : "modules/muninn/external/muninn/muninn/utils/StatisticsLogger.cpp",
			"sourceGroupIndex" : 0
		},
		{
			"backtrace" : 1,
			"compileGroupIndex" : 0,
			"path" : "modules/muninn/external/muninn/muninn/utils/MessageLogger.cpp",
			"sourceGroupIndex" : 0
		},
		{
			"backtrace" : 1,
			"compileGroupIndex" : 0,
			"path" : "modules/muninn/external/muninn/muninn/utils/StatisticsLogReader.cpp",
			"sourceGroupIndex" : 0
		},
		{
			"backtrace" : 1,
			"compileGroupIndex" : 0,
			"path" : "modules/muninn/external/muninn/muninn/utils/nonlinear/newton.cpp",
			"sourceGroupIndex" : 0
		},
		{
			"backtrace" : 1,
			"compileGroupIndex" : 0,
			"path" : "modules/muninn/external/muninn/muninn/WeightSchemes/LinearPolatedWeights.cpp",
			"sourceGroupIndex" : 0
		}
	],
	"type" : "STATIC_LIBRARY"
}
